pygame_util/__init__.py
pygame_util/button.py
pygame_util/color.py
pygame_util/dist/pygame_util-0.1.0.tar.gz
pygame_util/image.py
pygame_util/mapping.py
pygame_util/poetry.lock
pygame_util/position.py
pygame_util/text.py
pygame_util/timer.py
pygame_util/window.py
pygame_util-1.0.5.dist-info/LICENSE
pygame_util-1.0.5.dist-info/LICENSE.txt
pygame_util-1.0.5.dist-info/METADATA
pygame_util-1.0.5.dist-info/WHEEL
pygame_util-1.0.5.dist-info/RECORD
